gkfutils/__init__.py
gkfutils/__main__.py
gkfutils/main_test.py
gkfutils/main_test_gkfutils.py
gkfutils/utils.py
gkfutils/cv/__init__.py
gkfutils/cv/utils.py
gkfutils/cv/Paste_Object/__init__.py
gkfutils/cv/Paste_Object/add_black_bg.py
gkfutils/cv/Paste_Object/aug.py
gkfutils/cv/Paste_Object/cv_paste_object.py
gkfutils/cv/Paste_Object/paste_object_like_seamless_clone.py
gkfutils/cv/Paste_Object/pil_paste_object.py
gkfutils/cv/YOLO/__init__.py
gkfutils/cv/YOLO/common.py
gkfutils/cv/YOLO/yolo.py
gkfutils/cv/YOLO/yolo11_onnx_inference.py
gkfutils/cv/YOLO/yolov5_onnx_inference.py
gkfutils/cv/YOLO/yolov5_orig_onnx_inference_v2_OK.py
gkfutils/cv/YOLO/yolov5_simple.py
gkfutils/cv/YOLO/yolov5_simple_v2.py
gkfutils/cv/YOLO/yolov5_simple_v3.py
gkfutils/cv/YOLO/yolov8_onnx_inference.py
gkfutils/cv/YOLO/yolov8_orig_onnx_inference_v2_OK.py
gkfutils/cv/knowledge_distillation/__init__.py
gkfutils/cv/knowledge_distillation/main_test_knowledge_distillation.py
gkfutils/cv/lmdb/__init__.py
gkfutils/cv/lmdb/create_lmdb_dataset.py
gkfutils/cv/lmdb/merge_lmdb_dataset.py
gkfutils/cv/nn/__init__.py
gkfutils/cv/nn/cls_seg_net_v1.py
gkfutils/cv/nn/cls_seg_net_v2.py
gkfutils/cv/nn/model.py
gkfutils/cv/nn/backbone/__init__.py
gkfutils/cv/nn/backbone/mobilenet_v2.py
gkfutils/cv/nn/backbone/mobilenet_v3.py
gkfutils/cv/nn/backbone/resnet.py
gkfutils/cv/nn/backbone/rexnetv1.py
gkfutils/cv/nn/backbone/shufflenet.py
gkfutils/cv/nn/backbone/shufflenetv2.py
gkfutils/cv/nn/backbone/squeezenet.py
gkfutils/cv/nn/backbone/resnest/__init__.py
gkfutils/cv/nn/backbone/resnest/ablation.py
gkfutils/cv/nn/backbone/resnest/resnest.py
gkfutils/cv/nn/backbone/resnest/resnet.py
gkfutils/cv/nn/backbone/resnest/splat.py
gkfutils/cv/nn/head/ConvHead.py
gkfutils/cv/nn/head/DBHead.py
gkfutils/cv/nn/head/__init__.py
gkfutils/cv/nn/losses/DB_loss.py
gkfutils/cv/nn/losses/__init__.py
gkfutils/cv/nn/losses/basic_loss.py
gkfutils/cv/nn/losses/kd_loss.py
gkfutils/cv/nn/neck/FPEM_FFM.py
gkfutils/cv/nn/neck/FPN.py
gkfutils-1.1.9.dist-info/LICENSE
gkfutils-1.1.9.dist-info/METADATA
gkfutils-1.1.9.dist-info/WHEEL
gkfutils-1.1.9.dist-info/top_level.txt
gkfutils-1.1.9.dist-info/RECORD
