Metadata-Version: 2.1
Name: gkfutils
Version: 1.1.9
Summary: GraceKafuu utils
Author: GraceKafuu
Author-email: gracekafuu@gmail.com
Classifier: Programming Language :: Python :: 3
Classifier: License :: OSI Approved :: MIT License
Classifier: Operating System :: OS Independent
Requires-Python: >=3.6
License-File: LICENSE
